{
    "dataset_name": "breast_cancer",
    "generated_at": "2026-04-03T14:37:56.487220Z",
    "shape": {
        "rows": 569,
        "columns": 31
    },
    "target_column": "target",
    "feature_count": 30,
    "numeric_feature_count": 30,
    "categorical_feature_count": 0,
    "numeric_features": [
        "radius_mean",
        "texture_mean",
        "perimeter_mean",
        "area_mean",
        "smoothness_mean",
        "compactness_mean",
        "concavity_mean",
        "concave_points_mean",
        "symmetry_mean",
        "fractal_dimension_mean",
        "radius_se",
        "texture_se",
        "perimeter_se",
        "area_se",
        "smoothness_se",
        "compactness_se",
        "concavity_se",
        "concave_points_se",
        "symmetry_se",
        "fractal_dimension_se",
        "radius_worst",
        "texture_worst",
        "perimeter_worst",
        "area_worst",
        "smoothness_worst",
        "compactness_worst",
        "concavity_worst",
        "concave_points_worst",
        "symmetry_worst",
        "fractal_dimension_worst"
    ],
    "categorical_features": [],
    "target_distribution": {
        "0": 357,
        "1": 212
    },
    "target_rate_percent": {
        "0": 62.7417,
        "1": 37.2583
    },
    "class_balance_status": "reasonably_balanced",
    "missing_values": {
        "radius_mean": 0,
        "texture_mean": 0,
        "perimeter_mean": 0,
        "area_mean": 0,
        "smoothness_mean": 0,
        "compactness_mean": 0,
        "concavity_mean": 0,
        "concave_points_mean": 0,
        "symmetry_mean": 0,
        "fractal_dimension_mean": 0,
        "radius_se": 0,
        "texture_se": 0,
        "perimeter_se": 0,
        "area_se": 0,
        "smoothness_se": 0,
        "compactness_se": 0,
        "concavity_se": 0,
        "concave_points_se": 0,
        "symmetry_se": 0,
        "fractal_dimension_se": 0,
        "radius_worst": 0,
        "texture_worst": 0,
        "perimeter_worst": 0,
        "area_worst": 0,
        "smoothness_worst": 0,
        "compactness_worst": 0,
        "concavity_worst": 0,
        "concave_points_worst": 0,
        "symmetry_worst": 0,
        "fractal_dimension_worst": 0,
        "target": 0
    },
    "data_types": {
        "radius_mean": "float64",
        "texture_mean": "float64",
        "perimeter_mean": "float64",
        "area_mean": "float64",
        "smoothness_mean": "float64",
        "compactness_mean": "float64",
        "concavity_mean": "float64",
        "concave_points_mean": "float64",
        "symmetry_mean": "float64",
        "fractal_dimension_mean": "float64",
        "radius_se": "float64",
        "texture_se": "float64",
        "perimeter_se": "float64",
        "area_se": "float64",
        "smoothness_se": "float64",
        "compactness_se": "float64",
        "concavity_se": "float64",
        "concave_points_se": "float64",
        "symmetry_se": "float64",
        "fractal_dimension_se": "float64",
        "radius_worst": "float64",
        "texture_worst": "float64",
        "perimeter_worst": "float64",
        "area_worst": "float64",
        "smoothness_worst": "float64",
        "compactness_worst": "float64",
        "concavity_worst": "float64",
        "concave_points_worst": "float64",
        "symmetry_worst": "float64",
        "fractal_dimension_worst": "float64",
        "target": "int64"
    },
    "duplicate_rows": 0
}